skyway/__init__.py
skyway/account.py
skyway/utils.py
skyway/cloud/aws.py
skyway/cloud/azure.py
skyway/cloud/core.py
skyway/cloud/gcp.py
skyway/cloud/oci.py
skyway/cloud/slurm.py
skyway_cloud-2.0.5.data/data/data/skyway_alloc
skyway_cloud-2.0.5.data/data/data/skyway_batch
skyway_cloud-2.0.5.data/data/data/skyway_cancel
skyway_cloud-2.0.5.data/data/data/skyway_connect
skyway_cloud-2.0.5.data/data/data/skyway_dashboard
skyway_cloud-2.0.5.data/data/data/skyway_gui.py
skyway_cloud-2.0.5.data/data/data/skyway_interactive
skyway_cloud-2.0.5.data/data/data/skyway_list
skyway_cloud-2.0.5.data/data/data/skyway_nodetypes
skyway_cloud-2.0.5.data/data/data/skyway_transfer
skyway_cloud-2.0.5.data/data/data/skyway_usage
skyway_cloud-2.0.5.data/data/data/your_group-aws.yaml
skyway_cloud-2.0.5.data/data/data/your_group.pem
skyway_cloud-2.0.5.dist-info/LICENSE
skyway_cloud-2.0.5.dist-info/METADATA
skyway_cloud-2.0.5.dist-info/WHEEL
skyway_cloud-2.0.5.dist-info/top_level.txt
skyway_cloud-2.0.5.dist-info/RECORD
